sudoku_solver_tim/__init__.py
sudoku_solver_tim/puzzle.py
sudoku_solver_tim/strategies/__init__.py
sudoku_solver_tim/strategies/advanced/__init__.py
sudoku_solver_tim/strategies/advanced/hidden_pairs.py
sudoku_solver_tim/strategies/advanced/hidden_quads.py
sudoku_solver_tim/strategies/advanced/hidden_triples.py
sudoku_solver_tim/strategies/advanced/naked_pairs.py
sudoku_solver_tim/strategies/advanced/naked_quads.py
sudoku_solver_tim/strategies/advanced/naked_triples.py
sudoku_solver_tim/strategies/easy/__init__.py
sudoku_solver_tim/strategies/easy/single_candidates.py
sudoku_solver_tim/strategies/easy/single_position.py
sudoku_solver_tim/strategies/master/brute_force.py
sudoku_solver_tim/strategies/master/swordfish.py
sudoku_solver_tim/strategies/master/x_wings.py
sudoku_solver_tim/strategies/medium/__init__.py
sudoku_solver_tim/strategies/medium/candidate_lines.py
sudoku_solver_tim/strategies/medium/double_pairs.py
sudoku_solver_tim/strategies/medium/multiple_lines.py
sudoku_solver_tim-0.1.1.dist-info/METADATA
sudoku_solver_tim-0.1.1.dist-info/WHEEL
sudoku_solver_tim-0.1.1.dist-info/licenses/LICENSE
sudoku_solver_tim-0.1.1.dist-info/RECORD
