Metadata-Version: 2.4
Name: sudoku-solver-tim
Version: 0.1.1
Summary: Sudoku solver that will use successively more advanced techniques to solve the puzzle.
Project-URL: Homepage, https://github.com/timvink/sudoku-solver
Project-URL: Bug Tracker, https://github.com/timvink/sudoku-solver/issues
Author-email: Tim Vink <vinktim@gmail.com>
License: GPLv3
License-File: LICENSE
Classifier: License :: OSI Approved :: GNU General Public License v3 (GPLv3)
Classifier: Operating System :: OS Independent
Classifier: Programming Language :: Python
Classifier: Programming Language :: Python :: 3
Classifier: Programming Language :: Python :: 3.10
Classifier: Programming Language :: Python :: 3.11
Classifier: Programming Language :: Python :: 3.12
Classifier: Programming Language :: Python :: 3.13
Requires-Python: >=3.10
Requires-Dist: rich>=12.4.4
